{"data":{"_id":2000,"properties":{"id":{"name":"id","kind":"scalar","primary":true,"type":"uuid","array":false,"runtimeType":"string"},"items":{"name":"items","kind":"1:m","cascade":["persist"],"type":"CartItems","array":false,"runtimeType":"Collection<CartItems, object>"},"total":{"name":"total","kind":"scalar","getter":false,"setter":false,"type":"number","array":false,"runtimeType":"number"},"user":{"name":"user","kind":"1:1","cascade":["persist"],"nullable":false,"owner":true,"unique":true,"type":"Users","array":false,"runtimeType":"Users"}},"primaryKeys":["id"],"filters":{},"hooks":{},"indexes":[],"uniques":[],"className":"Carts","path":"./src/entities/cart.entity.ts","name":"Carts","abstract":false,"internal":true,"constructorParams":[],"toJsonParams":[],"useCache":true,"compositePK":false,"simplePK":true,"collection":"carts"},"origin":"./src/entities/cart.entity.ts","hash":"d23dde39ee341e6c8dea832a20fb9075","version":"6.4.0"}
